gdadorn
