Metadata-Version: 1.0
Name: gdadorn
Version: 0.1.1
Summary: jupyer的一些扩展修改，内存显示，下载限制等等
Home-page: https://github.com/similarface/gdadorn.git
Author: similarface
Author-email: similarface@gmail.com
License: MIT Licence
Platform: UNKNOWN
